test_case_generator_command/__init__.py
test_case_generator_command/admin.py
test_case_generator_command/apps.py
test_case_generator_command/models.py
test_case_generator_command/tests.py
test_case_generator_command/views.py
test_case_generator_command/management/__init__.py
test_case_generator_command/management/commands/__init__.py
test_case_generator_command/management/commands/generate_test_case.py
test_case_generator_command/migrations/__init__.py
django_rest_test_case_generator-0.2.1.dist-info/LICENSE.txt
django_rest_test_case_generator-0.2.1.dist-info/METADATA
django_rest_test_case_generator-0.2.1.dist-info/WHEEL
django_rest_test_case_generator-0.2.1.dist-info/top_level.txt
django_rest_test_case_generator-0.2.1.dist-info/RECORD
