Metadata-Version: 2.1
Name: django_rest_test_case_generator
Version: 0.2.1
Summary: Django command to generate test case for rest apis.
Home-page: https://github.com/Ronakjain515/django-rest-test-case-generator
Author: Ronak Jain
Author-email: jronak515@gmail.com
License: MIT
Project-URL: Bug Tracker, https://github.com/Ronakjain515/django-rest-test-case-generator/issues
Keywords: django,test case generator,rest apis,testing
Classifier: Programming Language :: Python :: 3
Classifier: License :: OSI Approved :: MIT License
Classifier: Operating System :: OS Independent
Requires-Python: >=3.6
License-File: LICENSE.txt
Requires-Dist: faker
Requires-Dist: astor
